example/cli.py
ops_plugin_example-0.1.6.dist-info/entry_points.txt
ops_plugin_example-0.1.6.dist-info/WHEEL
ops_plugin_example-0.1.6.dist-info/METADATA
ops_plugin_example-0.1.6.dist-info/RECORD
